confcls/__init__.py
confcls/configurable.py
confcls/dot_path.py
confcls/object.py
confcls-2.1.1.dist-info/LICENSE
confcls-2.1.1.dist-info/METADATA
confcls-2.1.1.dist-info/WHEEL
confcls-2.1.1.dist-info/RECORD
