Metadata-Version: 2.1
Name: confcls
Version: 2.1.1
Summary: Class instance configurator
Keywords: config,configuration
Author: Václav Krpec
Author-email: vencik@razdva.cz
Requires-Python: >=3.9,<4.0
Classifier: Development Status :: 5 - Production/Stable
Classifier: Intended Audience :: Developers
Classifier: License :: OSI Approved :: BSD License
Classifier: Programming Language :: Python :: 3
Classifier: Programming Language :: Python :: 3.9
Classifier: Programming Language :: Python :: 3.10
Classifier: Programming Language :: Python :: 3.11
Classifier: Programming Language :: Python :: 3.12
Provides-Extra: all
Requires-Dist: smart-open (>=7.0.4,<8.0.0) ; extra == "all"
Project-URL: Homepage, https://github.com/vencik/confcls
Project-URL: Repository, https://github.com/vencik/confcls
